docs/sain/boxed.html
docs/sain/cfg.html
docs/sain/collections.html
docs/sain/convert.html
docs/sain/default.html
docs/sain/error.html
docs/sain/futures.html
docs/sain/iter.html
docs/sain/macros.html
docs/sain/maybe_uninit.html
docs/sain/option.html
docs/sain/result.html
docs/sain/sync.html
docs/sain/time.html
docs/sain/collections/buf.html
docs/sain/collections/hash_map.html
docs/sain/collections/slice.html
docs/sain/collections/vec.html
sain/__init__.py
sain/__main__.py
sain/_misc.py
sain/analyze.py
sain/boxed.py
sain/cfg.py
sain/cfg.pyi
sain/default.py
sain/error.py
sain/futures.py
sain/iter.py
sain/macros.py
sain/maybe_uninit.py
sain/maybe_uninit.pyi
sain/option.py
sain/option.pyi
sain/py.typed
sain/result.py
sain/time.py
sain/collections/__init__.py
sain/collections/buf.py
sain/collections/slice.py
sain/collections/vec.py
sain/collections/hash_map/__init__.py
sain/collections/hash_map/base_iter.py
sain/convert/__init__.py
sain/sync/__init__.py
sain/sync/lazy.py
sain/sync/once.py
tests/sain/__init__.py
tests/sain/test_boxed.py
tests/sain/test_iter.py
tests/sain/test_maybe_uninit.py
tests/sain/test_option.py
tests/sain/test_result.py
tests/sain/collections/__init__.py
tests/sain/collections/test_buf.py
tests/sain/collections/test_slice.py
tests/sain/collections/test_vec.py
tests/sain/collections/hash_map/test_hash_map.py
tests/sain/sync/__init__.py
sain-1.4.0.dist-info/METADATA
sain-1.4.0.dist-info/WHEEL
sain-1.4.0.dist-info/licenses/LICENSE
sain-1.4.0.dist-info/RECORD
