Metadata-Version: 2.4
Name: sain
Version: 1.4.0
Summary: Write safe Python code like Rust
Project-URL: Repository, https://github.com/nxtlo/sain
Project-URL: Documentation, https://nxtlo.github.io/sain/sain.html
Project-URL: Changelog, https://github.com/nxtlo/sain/blob/master/CHANGELOG.md
Author-email: nxtlo <dhmony-99@hotmail.com>
License: BSD 3-Clause License
License-File: LICENSE
Keywords: buffer,collections,rust,utilities,vec
Classifier: Development Status :: 5 - Production/Stable
Classifier: Intended Audience :: Developers
Classifier: License :: OSI Approved :: BSD License
Classifier: Natural Language :: English
Classifier: Operating System :: OS Independent
Classifier: Programming Language :: Python :: 3.10
Classifier: Programming Language :: Python :: 3.11
Classifier: Programming Language :: Python :: 3.12
Classifier: Programming Language :: Python :: 3.13
Classifier: Programming Language :: Python :: 3.14
Classifier: Programming Language :: Python :: Implementation :: CPython
Classifier: Topic :: Software Development :: Libraries
Classifier: Topic :: Software Development :: Libraries :: Python Modules
Classifier: Typing :: Typed
Requires-Python: >=3.10.0
Requires-Dist: typing-extensions>=4.13.2
